genologics/__init__.py
genologics/config.py
genologics/constants.py
genologics/descriptors.py
genologics/entities.py
genologics/epp.py
genologics/internal_classes.py
genologics/lims.py
genologics/lims_utils.py
genologics/test_utils.py
genologics/version.py
genologics-2.0.1.dist-info/LICENSE
genologics-2.0.1.dist-info/METADATA
genologics-2.0.1.dist-info/WHEEL
genologics-2.0.1.dist-info/top_level.txt
genologics-2.0.1.dist-info/RECORD
